[
  {
    "_id": "6726de1ef07d988d1ad84877",
    "account": "WUSA",
    "date": 1730600477,
    "caption": "Embark on a flavour journey this fall and channel your inner chef!  [For More Information, Click View Post] ",
    "display_photo": "https://8d3cdb9a.rocketcdn.me/wp-content/uploads/2024/10/CambridgeMYOB_CamMYOB_Web-graphic.png",
    "event_details": {
      "is_event": true,
      "event_name": "Kitchener: Build Your Own Burger",
      "event_description": "Embark on a flavour journey this fall and channel your inner chef!  ... ",
      "categories": [
        "SOCIAL"
      ],
      "start_time": 1730739600,
      "end_time": 1730745000,
      "location": "10 Victoria Street South, Kitchener, ON"
    },
    "url": "https://wusa.ca/event/kitchener-build-your-own-burger/",
    "likes": 0.0,
    "embedded": ""
  },
  {
    "_id": "6726de1ff07d988d1ad84878",
    "account": "WUSA",
    "date": 1730600477,
    "caption": "Need a pick me up for the Monday blues? Join us every  [For More Information, Click View Post] ",
    "display_photo": "https://8d3cdb9a.rocketcdn.me/wp-content/uploads/2024/10/MondayFunday_Web.png",
    "event_details": {
      "is_event": true,
      "event_name": "Monday Funday",
      "event_description": "Need a pick me up for the Monday blues? Join us every  ... ",
      "categories": [
        "SOCIAL"
      ],
      "start_time": 1730764800,
      "end_time": 1730775600,
      "location": "200 University Ave W, SLC 3103"
    },
    "url": "https://wusa.ca/event/monday-funday-2/",
    "likes": 0.0,
    "embedded": ""
  },
  {
    "_id": "6726de1ff07d988d1ad84879",
    "account": "WUSA",
    "date": 1730600477,
    "caption": "Get ready to sip and shop at Pumpkin Spice and Thrifted Delights!  [For More Information, Click View Post] ",
    "display_photo": "https://8d3cdb9a.rocketcdn.me/wp-content/uploads/2024/10/PumpkinSpiceThrift_Web.png",
    "event_details": {
      "is_event": true,
      "event_name": "Pumpkin Spice &amp; Thrifted Delights: WUSA Thrift Sidewalk Sale",
      "event_description": "Get ready to sip and shop at Pumpkin Spice and Thrifted Delights!  ... ",
      "categories": [
        "SOCIAL"
      ],
      "start_time": 1730822400,
      "end_time": 1730833200,
      "location": "Student Life Centre, 200 University Ave W"
    },
    "url": "https://wusa.ca/event/wusa-thrift-sidewalk-sale-winter-edition/",
    "likes": 0.0,
    "embedded": ""
  },
  {
    "_id": "6726de20f07d988d1ad8487a",
    "account": "WUSA",
    "date": 1730600477,
    "caption": "Get your game on! Join us for our weekly board game nights  [For More Information, Click View Post] ",
    "display_photo": "https://8d3cdb9a.rocketcdn.me/wp-content/uploads/2024/10/Glow-Board-Game-Night_Web.png",
    "event_details": {
      "is_event": true,
      "event_name": "Board Game Night",
      "event_description": "Get your game on! Join us for our weekly board game nights  ... ",
      "categories": [
        "SOCIAL"
      ],
      "start_time": 1730851200,
      "end_time": 1730862000,
      "location": "200 University Ave W, SLC 3103"
    },
    "url": "https://wusa.ca/event/board-game-night/",
    "likes": 0.0,
    "embedded": ""
  },
  {
    "_id": "6726de21f07d988d1ad8487b",
    "account": "WUSA",
    "date": 1730600477,
    "caption": "Learn how to service your bike at our weekly workshops! Time:\u00a0Every Wednesday,  [For More Information, Click View Post] ",
    "display_photo": "https://8d3cdb9a.rocketcdn.me/wp-content/uploads/2024/07/Bike-Center_Workshop_Web-Event.png",
    "event_details": {
      "is_event": true,
      "event_name": "Bike 101 Workshops",
      "event_description": "Learn how to service your bike at our weekly workshops! Time:\u00a0Every Wednesday,  ... ",
      "categories": [
        "SOCIAL"
      ],
      "start_time": 1730916000,
      "end_time": 1730919600,
      "location": "SLC"
    },
    "url": "https://wusa.ca/event/bike-101-workshops/",
    "likes": 0.0,
    "embedded": ""
  },
  {
    "_id": "6726de22f07d988d1ad8487c",
    "account": "WUSA",
    "date": 1730600477,
    "caption": "PSA UW would like to invite you to Dholki Dhamaka Come out  [For More Information, Click View Post] ",
    "display_photo": "https://8d3cdb9a.rocketcdn.me/wp-content/uploads/2024/10/Dholki-Pic-e1730229053139.jpeg",
    "event_details": {
      "is_event": true,
      "event_name": "Dholki Ki Raat",
      "event_description": "PSA UW would like to invite you to Dholki Dhamaka Come out  ... ",
      "categories": [
        "SOCIAL"
      ],
      "start_time": 1730934000,
      "end_time": 1730952000,
      "location": "80 Schneider Ave"
    },
    "url": "https://wusa.ca/event/dholki-ki-raat/",
    "likes": 0.0,
    "embedded": ""
  },
  {
    "_id": "6726de23f07d988d1ad8487d",
    "account": "WUSA",
    "date": 1730600477,
    "caption": "Looking for a fun way to connect with fellow students on a  [For More Information, Click View Post] ",
    "display_photo": "https://8d3cdb9a.rocketcdn.me/wp-content/uploads/2024/10/Glow_Tea-Time-Talks_Web-1.png",
    "event_details": {
      "is_event": true,
      "event_name": "Tea Time",
      "event_description": "Looking for a fun way to connect with fellow students on a  ... ",
      "categories": [
        "SOCIAL"
      ],
      "start_time": 1730937600,
      "end_time": 1730948400,
      "location": "200 University Ave W, SLC 3103"
    },
    "url": "https://wusa.ca/event/tea-time/",
    "likes": 0.0,
    "embedded": ""
  },
  {
    "_id": "6726de23f07d988d1ad8487e",
    "account": "WUSA",
    "date": 1730600477,
    "caption": "Embark on a flavour journey this fall and channel your inner chef!  [For More Information, Click View Post] ",
    "display_photo": "https://8d3cdb9a.rocketcdn.me/wp-content/uploads/2024/10/CambridgeMYOB_CamMYOB_Web-graphic.png",
    "event_details": {
      "is_event": true,
      "event_name": "Stratford: Build Your Own Burger",
      "event_description": "Embark on a flavour journey this fall and channel your inner chef!  ... ",
      "categories": [
        "SOCIAL"
      ],
      "start_time": 1730998800,
      "end_time": 1731004200,
      "location": "125 St. Patrick St"
    },
    "url": "https://wusa.ca/event/stratford-build-your-own-burger/",
    "likes": 0.0,
    "embedded": ""
  },
  {
    "_id": "6726de24f07d988d1ad8487f",
    "account": "WUSA",
    "date": 1730600477,
    "caption": "Join us every Monday in the Glow Centre for our weekly Movie  [For More Information, Click View Post] ",
    "display_photo": "https://8d3cdb9a.rocketcdn.me/wp-content/uploads/2024/10/Glow_Music-and-Movie-Night_Web-1.png",
    "event_details": {
      "is_event": true,
      "event_name": "Movie Night",
      "event_description": "Join us every Monday in the Glow Centre for our weekly Movie  ... ",
      "categories": [
        "SOCIAL"
      ],
      "start_time": 1731024000,
      "end_time": 1731034800,
      "location": "200 University Ave W, SLC 3103"
    },
    "url": "https://wusa.ca/event/movie-night/",
    "likes": 0.0,
    "embedded": ""
  },
  {
    "_id": "6726de25f07d988d1ad84880",
    "account": "WUSA",
    "date": 1730600477,
    "caption": "Looking for a fun and unique getaway this Fall? Join the International  [For More Information, Click View Post] ",
    "display_photo": "https://8d3cdb9a.rocketcdn.me/wp-content/uploads/2024/10/NiagaraFalls_Web.png",
    "event_details": {
      "is_event": true,
      "event_name": "Niagara Falls Trip",
      "event_description": "Looking for a fun and unique getaway this Fall? Join the International  ... ",
      "categories": [
        "SOCIAL"
      ],
      "start_time": 1731160800,
      "end_time": 1731196800,
      "location": "6650 Niagara River Pkwy"
    },
    "url": "https://wusa.ca/event/niagara-falls-trip/",
    "likes": 0.0,
    "embedded": ""
  },
  {
    "_id": "6726de26f07d988d1ad84881",
    "account": "WUSA",
    "date": 1730600477,
    "caption": "Join the Women\\'s Centre on Monday, November 11th in the SLC Lower  [For More Information, Click View Post] ",
    "display_photo": "https://8d3cdb9a.rocketcdn.me/wp-content/uploads/2024/10/Love-your-body-bust-casting_Web.png",
    "event_details": {
      "is_event": true,
      "event_name": "Love Your Body Week: Chest Casting",
      "event_description": "Join the Women\\'s Centre on Monday, November 11th in the SLC Lower  ... ",
      "categories": [
        "SOCIAL"
      ],
      "start_time": 1731362400,
      "end_time": 1731369600,
      "location": "200 University Ave W"
    },
    "url": "https://wusa.ca/event/love-your-body-week-chest-casting/",
    "likes": 0.0,
    "embedded": ""
  },
  {
    "_id": "6726de27f07d988d1ad84882",
    "account": "WUSA",
    "date": 1730600477,
    "caption": "Are you looking for a fun night to destress just before exams?  [For More Information, Click View Post] ",
    "display_photo": "https://8d3cdb9a.rocketcdn.me/wp-content/uploads/2024/10/OCC-Dance-Party_Web.png",
    "event_details": {
      "is_event": true,
      "event_name": "Disco After Dark &#8211; All Ages",
      "event_description": "Are you looking for a fun night to destress just before exams?  ... ",
      "categories": [
        "SOCIAL"
      ],
      "start_time": 1731549600,
      "end_time": 1731556800,
      "location": "200 University Ave W."
    },
    "url": "https://wusa.ca/event/disco-after-dark/",
    "likes": 0.0,
    "embedded": ""
  },
  {
    "_id": "6726de28f07d988d1ad84883",
    "account": "WUSA",
    "date": 1730600477,
    "caption": "Math students and professors are invited to enjoy food and drinks at  [For More Information, Click View Post] ",
    "display_photo": "https://8d3cdb9a.rocketcdn.me/wp-content/uploads/2024/10/Untitled-design-11.png",
    "event_details": {
      "is_event": true,
      "event_name": "Party with Profs",
      "event_description": "Math students and professors are invited to enjoy food and drinks at  ... ",
      "categories": [
        "SOCIAL"
      ],
      "start_time": 1731697200,
      "end_time": 1731704400,
      "location": "South Campus Hall, Gradhouse Green, 200 University Ave W,"
    },
    "url": "https://wusa.ca/event/party-with-profs/",
    "likes": 0.0,
    "embedded": ""
  },
  {
    "_id": "6726de28f07d988d1ad84884",
    "account": "WUSA",
    "date": 1730600477,
    "caption": "The UWAC Team is excited to announce that registration for Canada\\'s premier  [For More Information, Click View Post] ",
    "display_photo": "https://8d3cdb9a.rocketcdn.me/wp-content/uploads/2024/10/Untitled-design-11-1.png",
    "event_details": {
      "is_event": true,
      "event_name": "University of Waterloo Accounting Conference 2024",
      "event_description": "The UWAC Team is excited to announce that registration for Canada\\'s premier  ... ",
      "categories": [
        "SOCIAL"
      ],
      "start_time": 1731762000,
      "end_time": 1731801600,
      "location": "200 University Ave W"
    },
    "url": "https://wusa.ca/event/university-of-waterloo-accounting-conference-2024/",
    "likes": 0.0,
    "embedded": ""
  },
  {
    "_id": "6726de29f07d988d1ad84885",
    "account": "WUSA",
    "date": 1730600477,
    "caption": "Mates is excited to announce that we are bringing back safeTALK training  [For More Information, Click View Post] ",
    "display_photo": "https://8d3cdb9a.rocketcdn.me/wp-content/uploads/2024/09/Web.png",
    "event_details": {
      "is_event": true,
      "event_name": "safeTALK Training",
      "event_description": "Mates is excited to announce that we are bringing back safeTALK training  ... ",
      "categories": [
        "SOCIAL"
      ],
      "start_time": 1731767400,
      "end_time": 1731780000,
      "location": null
    },
    "url": "https://wusa.ca/event/safetalk-training-3/",
    "likes": 0.0,
    "embedded": ""
  },
  {
    "_id": "6726de2af07d988d1ad84886",
    "account": "WUSA",
    "date": 1730600477,
    "caption": "\ud83d\udce2 Join the Women\\' Centre on Monday, November 18th from 5 -  [For More Information, Click View Post] ",
    "display_photo": "https://8d3cdb9a.rocketcdn.me/wp-content/uploads/2024/10/WC-Fitness_Web-banner.png",
    "event_details": {
      "is_event": true,
      "event_name": "Empowering Fitness: Foundations of Strength Training",
      "event_description": "\ud83d\udce2 Join the Women\\' Centre on Monday, November 18th from 5 -  ... ",
      "categories": [
        "SOCIAL"
      ],
      "start_time": 1731967200,
      "end_time": 1731970800,
      "location": null
    },
    "url": "https://wusa.ca/event/empowering-fitness-foundations-of-strength-training/",
    "likes": 0.0,
    "embedded": ""
  },
  {
    "_id": "6726de2bf07d988d1ad84887",
    "account": "WUSA",
    "date": 1730600477,
    "caption": "Sweet treats and unique delights await on Wednesday, November 20th! Join Mates  [For More Information, Click View Post] ",
    "display_photo": "https://8d3cdb9a.rocketcdn.me/wp-content/uploads/2024/10/CookieDecorating_Web.png",
    "event_details": {
      "is_event": true,
      "event_name": "Cookie Decorating",
      "event_description": "Sweet treats and unique delights await on Wednesday, November 20th! Join Mates  ... ",
      "categories": [
        "SOCIAL"
      ],
      "start_time": 1732143600,
      "end_time": 1732150800,
      "location": "200 University Ave W."
    },
    "url": "https://wusa.ca/event/cookie-decorating/",
    "likes": 0.0,
    "embedded": ""
  },
  {
    "_id": "6726de2cf07d988d1ad84888",
    "account": "WUSA",
    "date": 1730600477,
    "caption": "Watch the live stream for November\\'s board meeting here!&lt;/p&gt;\\n [For More Information, Click View Post] ",
    "display_photo": "https://8d3cdb9a.rocketcdn.me/wp-content/uploads/2024/10/Board-Thumbnail-scaled.jpeg",
    "event_details": {
      "is_event": true,
      "event_name": "November Board Meeting",
      "event_description": "Watch the live stream for November\\'s board meeting here!&lt;/p&gt;\\n ... ",
      "categories": [
        "SOCIAL"
      ],
      "start_time": 1732230000,
      "end_time": 1732237200,
      "location": null
    },
    "url": "https://wusa.ca/event/board-meeting-nov/",
    "likes": 0.0,
    "embedded": ""
  },
  {
    "_id": "6726de2df07d988d1ad84889",
    "account": "WUSA",
    "date": 1730600477,
    "caption": "Wellness Week is around the corner with an array of exciting activities  [For More Information, Click View Post] ",
    "display_photo": "https://8d3cdb9a.rocketcdn.me/wp-content/uploads/2024/10/Wellness-Week_Web.png",
    "event_details": {
      "is_event": true,
      "event_name": "Wellness Week",
      "event_description": "Wellness Week is around the corner with an array of exciting activities  ... ",
      "categories": [
        "SOCIAL"
      ],
      "start_time": 1732563000,
      "end_time": 1732570200,
      "location": "200 University Ave W, SLC"
    },
    "url": "https://wusa.ca/event/wellness-week/",
    "likes": 0.0,
    "embedded": ""
  },
  {
    "_id": "6726de2ef07d988d1ad8488a",
    "account": "WUSA",
    "date": 1730600477,
    "caption": "Students often have many questions when it comes to their rights when  [For More Information, Click View Post] ",
    "display_photo": "https://8d3cdb9a.rocketcdn.me/wp-content/uploads/2024/09/TenantRightsEvents_Events.png",
    "event_details": {
      "is_event": true,
      "event_name": "Student Tenancy Legal Sessions: Virtual Event",
      "event_description": "Students often have many questions when it comes to their rights when  ... ",
      "categories": [
        "SOCIAL"
      ],
      "start_time": 1732741200,
      "end_time": 1732753800,
      "location": null
    },
    "url": "https://wusa.ca/event/student-tenancy-legal-sessions/",
    "likes": 0.0,
    "embedded": ""
  },
  {
    "_id": "6726de2ef07d988d1ad8488b",
    "account": "WUSA",
    "date": 1730600477,
    "caption": "The Science Society Annual Sciball - Will be held at St. George  [For More Information, Click View Post] ",
    "display_photo": "https://8d3cdb9a.rocketcdn.me/wp-content/uploads/2024/10/SCIBALL-24-1-e1730233833854.png",
    "event_details": {
      "is_event": true,
      "event_name": "Sciball 2024 &#8211; A Winter Night&#8217;s Dream",
      "event_description": "The Science Society Annual Sciball - Will be held at St. George  ... ",
      "categories": [
        "SOCIAL"
      ],
      "start_time": 1732752000,
      "end_time": 1732770000,
      "location": "665 King St N"
    },
    "url": "https://wusa.ca/event/sciball-2024-a-winter-nights-dream/",
    "likes": 0.0,
    "embedded": ""
  },
  {
    "_id": "6726de2ff07d988d1ad8488c",
    "account": "WUSA",
    "date": 1730600477,
    "caption": "Wellness Week is around the corner with an array of exciting activities  [For More Information, Click View Post] ",
    "display_photo": "https://8d3cdb9a.rocketcdn.me/wp-content/uploads/2024/10/Wellness-Week_Web.png",
    "event_details": {
      "is_event": true,
      "event_name": "Wellness Week",
      "event_description": "Wellness Week is around the corner with an array of exciting activities  ... ",
      "categories": [
        "SOCIAL"
      ],
      "start_time": 1732822200,
      "end_time": 1732829400,
      "location": "200 University Ave W, SLC"
    },
    "url": "https://wusa.ca/event/wellness-week-2/",
    "likes": 0.0,
    "embedded": ""
  },
  {
    "_id": "6726e06ff07d988d1ad8488f",
    "url": "DBzMzV5Sm2G",
    "likes": 38,
    "display_photo": "https://instagram.fyzd1-2.fna.fbcdn.net/v/t51.29350-15/465281282_1096427888534351_3340083778167546337_n.jpg?stp=dst-jpg_e35&efg=eyJ2ZW5jb2RlX3RhZyI6ImltYWdlX3VybGdlbi4xMDgweDEwODAuc2RyLmYyOTM1MC5kZWZhdWx0X2ltYWdlIn0&_nc_ht=instagram.fyzd1-2.fna.fbcdn.net&_nc_cat=111&_nc_ohc=d7-B_5aer7UQ7kNvgF1829R&_nc_gid=3d3c42ee19b54c2cb7b2cc01093b16ec&edm=AEhyXUkBAAAA&ccb=7-5&ig_cache_key=MzQ5MTE5MDQ0MDkwMzQ3MDQ3MA%3D%3D.3-ccb7-5&oh=00_AYAHkHU7rcX7zsAVQXf8la56wGaDgTPzxsgnfqRLubwkog&oe=672CA1FF&_nc_sid=8f1549",
    "account": "uwaterloodsc",
    "date": "2024-10-31 19:19:13",
    "caption": "\ud83e\udd71 Need to catch a break from studying?\ud83c\udfa4  Come out to DSC\u2019s Karaoke Night for a night of music and fun~! Bring your friends and be prepared to sing your stress away to unforgettable tunes \ud83c\udfb6 \ud83d\ude0b  Cotton candy and bubble tea will be provided! \ud83c\udf6d\ud83e\uddcb\ud83d\uddd3\ufe0f Monday, November 4th\u231b  5:30-6:30 pm\ud83d\udccd MC 2054#uwdatascience #datascience #uwmath #waterloomath #waterlooengineering #uwaterloo #uwaterlooengineering #uwaterloomath #singing #karaoke #music #clubs #mathsoc #wusa",
    "accessibility_caption": "None",
    "embedded": "",
    "event_details": {
      "is_event": true,
      "event_name": "DSC\u2019s Karaoke Night",
      "event_description": "Karaoke Night with Cotton candy and bubble tea",
      "event_categories": [
        "MUSIC"
      ],
      "start_time": 1730759400.0,
      "end_time": 1730763000.0,
      "location": "MC 2054"
    }
  },
  {
    "_id": "6726e070f07d988d1ad84890",
    "url": "DB1Zsqrgvg3",
    "likes": 15,
    "display_photo": "https://instagram.fyzd1-2.fna.fbcdn.net/v/t51.29350-15/465078610_1073561277479395_3869695992435084541_n.heic?stp=dst-jpg_e35&efg=eyJ2ZW5jb2RlX3RhZyI6ImltYWdlX3VybGdlbi4xNDQweDE3Nzkuc2RyLmYyOTM1MC5kZWZhdWx0X2ltYWdlIn0&_nc_ht=instagram.fyzd1-2.fna.fbcdn.net&_nc_cat=107&_nc_ohc=5VYRXHuvxwMQ7kNvgHpUChm&_nc_gid=e87ae9bf44b54d78b4c2f30dabdbeb5c&edm=AEhyXUkBAAAA&ccb=7-5&ig_cache_key=MzQ5MTgxMDEwNjc0MjYwMTc4Mw%3D%3D.3-ccb7-5&oh=00_AYAhJuZLnb3LLsI69r1kBqi5_MY8atDe3UMWt_eKfWtClg&oe=672CB1D8&_nc_sid=8f1549",
    "account": "uwstreetdance",
    "date": "2024-11-01 15:50:20",
    "caption": "Next monday, we have @raymondrussell_ teaching Jookin, glides, and footwork \ud83d\udd25. This one\u2019s for all levels, so don\u2019t stress if you\u2019re new. Meet us 8-10pm in the SLC lower atrium, and don\u2019t forget to hit up the UWSD crew server (link in bio \ud83d\udc40). See y\u2019all there!#dance #streetdance #waterloo #uwaterloo",
    "accessibility_caption": "None",
    "embedded": "",
    "event_details": {
      "is_event": true,
      "event_name": "UW Street Dance Class",
      "event_description": "Jookin, glides, and footwork class for all levels",
      "event_categories": [
        "DANCE"
      ],
      "start_time": 1730941200.0,
      "end_time": 1730948400.0,
      "location": "SLC Lower Atrium"
    }
  },
  {
    "_id": "6726e071f07d988d1ad84891",
    "url": "DB2VF2es5in",
    "likes": 22,
    "display_photo": "https://instagram.fyzd1-2.fna.fbcdn.net/v/t51.29350-15/465055906_902458111474933_6164465882353648756_n.jpg?stp=dst-jpg_e15&efg=eyJ2ZW5jb2RlX3RhZyI6ImltYWdlX3VybGdlbi4xMDgweDEwODAuc2RyLmYyOTM1MC5kZWZhdWx0X2ltYWdlIn0&_nc_ht=instagram.fyzd1-2.fna.fbcdn.net&_nc_cat=101&_nc_ohc=T0ljfmBSthIQ7kNvgEBhHZr&_nc_gid=73408bb47b684d5eb114de0e883a7604&edm=AEhyXUkBAAAA&ccb=7-5&ig_cache_key=MzQ5MjA3MTMyMjE0MzY2MDE5OQ%3D%3D.3-ccb7-5&oh=00_AYAPMotHdc6qmcJiVZPMG9UldJJSo1TC-gQ6Kc04nGP-KA&oe=672CA32B&_nc_sid=8f1549",
    "account": "uw_bmsa",
    "date": "2024-11-02 00:29:23",
    "caption": "Join us on Monday November 4th from 5:30-7:30pm at RCH 302 for a fun review session on Chem 120\u2019s Test 2\ud83d\udcda! Food and beverages will be included along with a jeopardy game to test your knowledge! \ud83e\uddea",
    "accessibility_caption": "None",
    "embedded": "",
    "event_details": {
      "is_event": true,
      "event_name": "UW BMSA Chem 120 Test 2 Review Session",
      "event_description": "Chem 120 Test 2 review session with jeopardy game and food",
      "event_categories": [
        "CULTURE"
      ],
      "start_time": 1730759400.0,
      "end_time": 1730766600.0,
      "location": "RCH 302"
    }
  },
  {
    "_id": "6726e342670f678f900cfe53",
    "url": "DB4Ll3zR5jQ",
    "likes": 61,
    "display_photo": "https://instagram.fyzd1-2.fna.fbcdn.net/v/t51.2885-15/465245310_18095720176472713_8605593603791544655_n.jpg?stp=dst-jpg_e15&efg=eyJ2ZW5jb2RlX3RhZyI6ImltYWdlX3VybGdlbi4xMDgweDEwODAuc2RyLmY3NTc2MS5kZWZhdWx0X2ltYWdlIn0&_nc_ht=instagram.fyzd1-2.fna.fbcdn.net&_nc_cat=101&_nc_ohc=VnCReNPFOUkQ7kNvgFFBCS7&_nc_gid=3cca83dd1fb04695a9b6cb799514563a&edm=AEhyXUkBAAAA&ccb=7-5&ig_cache_key=MzQ5MjU5MjQ5MjA3NDIxMTUzNg%3D%3D.3-ccb7-5&oh=00_AYB69JxLZi6Gwzvt1sKI8g8Z5axuXAY6Rm3zCSnUb4TEdw&oe=672C93AE&_nc_sid=8f1549",
    "account": "uw_ux",
    "date": "2024-11-02 17:44:51",
    "caption": "Ready to put your design skills to the test?@uw_ux is hosting a friendly design SHOWDOWN, a thrilling event where you can have fun with design and make fellow designer friends \ud83c\udfa8\ud83d\udc40 Open to all students of any program, and designers of all levels!When is this happening?\ud83d\udcc6 Friday, November 8th 2024\u23f0 6:30 PM - 8:30 PM EST\ud83d\udccd Located @ UW SCH 228\ud83d\udc49 Luma link in bio to register!Here, you\u2019ll be able to\u2026\ud83e\udd14 Find solutions to a given problem statement\ud83d\udd0e Work in small teams and make new design friends!\ud83d\udcad Design with constraints (and\u2026 against a sabotage?!)Can\u2019t wait to see you there! \ud83e\udd73#uwaterloo #uxdesign #uxuidesign",
    "accessibility_caption": "None",
    "embedded": "",
    "event_details": {
      "is_event": true,
      "event_name": "uw_ux Design Showdown",
      "event_description": "A friendly design competition for all students and designers.",
      "event_categories": [
        "DESIGN"
      ],
      "start_time": 1731108600.0,
      "end_time": 1731115800.0,
      "location": "UW SCH 228 Luma"
    }
  },
  {
    "_id": "6726e344670f678f900cfe55",
    "url": "DB1Zsqrgvg3",
    "likes": 15,
    "display_photo": "https://instagram.fyzd1-2.fna.fbcdn.net/v/t51.29350-15/465078610_1073561277479395_3869695992435084541_n.heic?stp=dst-jpg_e35&efg=eyJ2ZW5jb2RlX3RhZyI6ImltYWdlX3VybGdlbi4xNDQweDE3Nzkuc2RyLmYyOTM1MC5kZWZhdWx0X2ltYWdlIn0&_nc_ht=instagram.fyzd1-2.fna.fbcdn.net&_nc_cat=107&_nc_ohc=5VYRXHuvxwMQ7kNvgHpUChm&_nc_gid=e87ae9bf44b54d78b4c2f30dabdbeb5c&edm=AEhyXUkBAAAA&ccb=7-5&ig_cache_key=MzQ5MTgxMDEwNjc0MjYwMTc4Mw%3D%3D.3-ccb7-5&oh=00_AYAhJuZLnb3LLsI69r1kBqi5_MY8atDe3UMWt_eKfWtClg&oe=672CB1D8&_nc_sid=8f1549",
    "account": "uwstreetdance",
    "date": "2024-11-01 15:50:20",
    "caption": "Next monday, we have @raymondrussell_ teaching Jookin, glides, and footwork \ud83d\udd25. This one\u2019s for all levels, so don\u2019t stress if you\u2019re new. Meet us 8-10pm in the SLC lower atrium, and don\u2019t forget to hit up the UWSD crew server (link in bio \ud83d\udc40). See y\u2019all there!#dance #streetdance #waterloo #uwaterloo",
    "accessibility_caption": "None",
    "embedded": "",
    "event_details": {
      "is_event": true,
      "event_name": "UW Street Dance Class",
      "event_description": "Jookin, glides, and footwork class for all levels",
      "event_categories": [
        "MUSIC",
        "CULTURE",
        "SPORTS"
      ],
      "start_time": 1730941200.0,
      "end_time": 1730948400.0,
      "location": "SLC Lower Atrium"
    }
  },
  {
    "_id": "6726e347670f678f900cfe57",
    "url": "DBy-KsJJ2E9",
    "likes": 34,
    "display_photo": "https://instagram.fyzd1-3.fna.fbcdn.net/v/t51.29350-15/465059532_542790188461980_1885277853850208716_n.jpg?stp=dst-jpg_e35&efg=eyJ2ZW5jb2RlX3RhZyI6ImltYWdlX3VybGdlbi4xMDgweDEwODAuc2RyLmYyOTM1MC5kZWZhdWx0X2ltYWdlIn0&_nc_ht=instagram.fyzd1-3.fna.fbcdn.net&_nc_cat=100&_nc_ohc=n4QpEmDU8qMQ7kNvgGp1uls&_nc_gid=f68c9b3663754e3e8e8d5389d7782671&edm=AEhyXUkBAAAA&ccb=7-5&ig_cache_key=MzQ5MTEyNjA3NDY0MjIyNzUxNw%3D%3D.3-ccb7-5&oh=00_AYCs51w0l5XVT2M9z3q7T66pg0Qp1fBEz-gD67qMTRkxkQ&oe=672CA990&_nc_sid=8f1549",
    "account": "uw.movie.watchers",
    "date": "2024-10-31 17:11:20",
    "caption": "Tomorrow night come to movie club, waterboo and medlife\u2019s! double feature movie night!! One Halloween movie and one Christmas horror movie to get people into the new season coming up!!We will have free snacks courtesy of medlife (while supplies last!!)Hope to see you tomorrow night!!",
    "accessibility_caption": "None",
    "embedded": "",
    "event_details": {
      "is_event": true,
      "event_name": "Movie Club - Double Feature",
      "event_description": "Double feature movie night with Halloween and Christmas horror movies",
      "event_categories": [
        "CULTURE"
      ],
      "start_time": 1730347200.0,
      "end_time": 1730347200.0,
      "location": "null"
    }
  }
]